Workbook

Sheet Guide
A1: Istito'ah Tracker: data template
A2: depositor-plan.xlsx
A4: What this is | B4: Two sheets: the settings for one depositor, and the year-by-year projection the page works out from them. In Excel the projection is live formulas, so changing a setting changes it. Aiman's settings are shown.
A5: Apakah ini | B5: Dua helaian: tetapan bagi seorang pendeposit, dan unjuran tahun demi tahun yang dikira daripadanya. Dalam Excel unjuran ialah formula hidup, jadi menukar tetapan akan mengubahnya. Tetapan Aiman dipaparkan.
A6: Sample rows are made up. Keep the header row; replace the rows below it. Gold cells are worked out by formula. / Baris contoh adalah rekaan. Kekalkan baris tajuk.
A8: Sheet | B8: Column | C8: Header | D8: Type | E8: Meaning (EN) | F8: Maksud (BM) | G8: Allowed values
A9: Inputs | B9: A | C9: setting | D9: text | E9: What the value is. | F9: Maksud nilai.
A10: Inputs | B10: B | C10: value | D10: text | E10: The depositor's figure. Change these. | F10: Angka pendeposit. Ubah nilai ini.
A11: Inputs | B11: C | C11: note | D11: text | E11: Where the figure comes from. | F11: Dari mana angka itu datang.
A12: Projection | B12: A | C12: year_no | D12: number | E12: Year of saving, from October 2026. | F12: Tahun menyimpan, mulai Oktober 2026.
A13: Projection | B13: B | C13: to_month | D13: text | E13: The year ends in this month. | F13: Tahun berakhir pada bulan ini.
A14: Projection | B14: C | C14: opening_rm | D14: RM (formula) | E14: Balance at the start of the year: last year's closing balance. | F14: Baki awal tahun: baki akhir tahun sebelumnya.
A15: Projection | B15: D | C15: deposits_rm | D15: RM (formula) | E15: Twelve monthly deposits. | F15: Dua belas simpanan bulanan.
A16: Projection | B16: E | C16: profit_rm | D16: RM (formula) | E16: Profit distribution added at year end on the balance. | F16: Agihan keuntungan ditambah pada akhir tahun ke atas baki.
A17: Projection | B17: F | C17: closing_rm | D17: RM (formula) | E17: Opening + deposits + profit. | F17: Baki awal + simpanan + keuntungan.
A18: Projection | B18: G | C18: passes | D18: text (formula) | E18: The amounts passed during the year. | F18: Amaun yang dilepasi dalam tahun itu.
A20: Step | B20: Sheet | C20: Columns | D20: What it counts (EN) | E20: Apa yang dikira (BM) | F20: Feeds | G20: Menyalurkan
A21: 1 | B21: Projection | C21: D | D21: Every month: add the deposit: RM150 a month goes in, RM1,800 a year (column D). | E21: Setiap bulan: tambah simpanan: RM150 sebulan dimasukkan, RM1,800 setahun (lajur D). | F21: Green line on the chart | G21: Garis hijau pada carta
A22: 2 | B22: Projection | C22: E | D22: Every 12 months: add the profit: 3.5% of the balance at year end (column E). An assumption you can change; TH never guarantees it. | E22: Setiap 12 bulan: tambah keuntungan: 3.5% daripada baki pada akhir tahun (lajur E). Andaian yang boleh diubah; TH tidak menjaminnya. | F22: Green line on the chart | G22: Garis hijau pada carta
A23: 3 | B23: Projection | C23: F, G | D23: Milestone: first month past RM15,000: The year is found here (G); the page then steps month by month to give the exact date. | E23: Pencapaian: bulan pertama melepasi RM15,000: Tahunnya dikenal pasti di sini (G); halaman kemudian mengira bulan demi bulan untuk tarikh tepat. | F23: Milestones list | G23: Senarai pencapaian
A24: 4 | B24: Inputs | C24: B | D24: With the programme's extra RM50: The same sums with RM200 a month instead of RM150. | E24: Dengan tambahan RM50 daripada program: Kiraan yang sama dengan RM200 sebulan, bukan RM150. | F24: Dashed gold line | G24: Garis emas putus-putus

Sheet Inputs
A1: setting | B1: value | C1: note
A2: age | B2: 24 | C2: Age today
A3: balance_today_rm | B3: 1800 | C3: Real data: balance_rm in the Monthly snapshot
A4: monthly_deposit_rm | B4: 150 | C4: Real data: average deposit_this_month_rm
A5: extra_from_programme_rm | B5: 50 | C5: Extra a month agreed in a literacy programme
A6: pay_category | B6: M40 | C6: B40, M40 or T20
A7: registered | B7: N | C7: Y adds the 31 Dec 2028 deadline
A8: kos_haji_rm | B8: 33300 | C8: TH, 1448H/2027M
A9: profit_pct | B9: 3.5 | C9: Assumed yearly profit distribution; never guaranteed
A10: own_payment_rm | B10: =IF(B6="B40",15000,IF(B6="M40",23500,33300)) | C10: Worked out from pay_category

Sheet Projection
A1: year_no | B1: to_month | C1: opening_rm | D1: deposits_rm | E1: profit_rm | F1: closing_rm | G1: passes
A2: 1 | B2: Sep 2027 | C2: =Inputs!B3 | D2: =12*Inputs!$B$4 | E2: =ROUND((C2+D2)*Inputs!$B$9/100,2) | F2: =C2+D2+E2 | G2: =TRIM(IF(AND(C2<15000,F2>=15000),"RM15,000 gate ","")&IF(AND(C2<Inputs!$B$10,F2>=Inputs!$B$10),"Own payment",""))
A3: 2 | B3: Sep 2028 | C3: =F2 | D3: =12*Inputs!$B$4 | E3: =ROUND((C3+D3)*Inputs!$B$9/100,2) | F3: =C3+D3+E3 | G3: =TRIM(IF(AND(C3<15000,F3>=15000),"RM15,000 gate ","")&IF(AND(C3<Inputs!$B$10,F3>=Inputs!$B$10),"Own payment",""))
A4: 3 | B4: Sep 2029 | C4: =F3 | D4: =12*Inputs!$B$4 | E4: =ROUND((C4+D4)*Inputs!$B$9/100,2) | F4: =C4+D4+E4 | G4: =TRIM(IF(AND(C4<15000,F4>=15000),"RM15,000 gate ","")&IF(AND(C4<Inputs!$B$10,F4>=Inputs!$B$10),"Own payment",""))
A5: 4 | B5: Sep 2030 | C5: =F4 | D5: =12*Inputs!$B$4 | E5: =ROUND((C5+D5)*Inputs!$B$9/100,2) | F5: =C5+D5+E5 | G5: =TRIM(IF(AND(C5<15000,F5>=15000),"RM15,000 gate ","")&IF(AND(C5<Inputs!$B$10,F5>=Inputs!$B$10),"Own payment",""))
A6: 5 | B6: Sep 2031 | C6: =F5 | D6: =12*Inputs!$B$4 | E6: =ROUND((C6+D6)*Inputs!$B$9/100,2) | F6: =C6+D6+E6 | G6: =TRIM(IF(AND(C6<15000,F6>=15000),"RM15,000 gate ","")&IF(AND(C6<Inputs!$B$10,F6>=Inputs!$B$10),"Own payment",""))
A7: 6 | B7: Sep 2032 | C7: =F6 | D7: =12*Inputs!$B$4 | E7: =ROUND((C7+D7)*Inputs!$B$9/100,2) | F7: =C7+D7+E7 | G7: =TRIM(IF(AND(C7<15000,F7>=15000),"RM15,000 gate ","")&IF(AND(C7<Inputs!$B$10,F7>=Inputs!$B$10),"Own payment",""))
A8: 7 | B8: Sep 2033 | C8: =F7 | D8: =12*Inputs!$B$4 | E8: =ROUND((C8+D8)*Inputs!$B$9/100,2) | F8: =C8+D8+E8 | G8: =TRIM(IF(AND(C8<15000,F8>=15000),"RM15,000 gate ","")&IF(AND(C8<Inputs!$B$10,F8>=Inputs!$B$10),"Own payment",""))
A9: 8 | B9: Sep 2034 | C9: =F8 | D9: =12*Inputs!$B$4 | E9: =ROUND((C9+D9)*Inputs!$B$9/100,2) | F9: =C9+D9+E9 | G9: =TRIM(IF(AND(C9<15000,F9>=15000),"RM15,000 gate ","")&IF(AND(C9<Inputs!$B$10,F9>=Inputs!$B$10),"Own payment",""))
A10: 9 | B10: Sep 2035 | C10: =F9 | D10: =12*Inputs!$B$4 | E10: =ROUND((C10+D10)*Inputs!$B$9/100,2) | F10: =C10+D10+E10 | G10: =TRIM(IF(AND(C10<15000,F10>=15000),"RM15,000 gate ","")&IF(AND(C10<Inputs!$B$10,F10>=Inputs!$B$10),"Own payment",""))
A11: 10 | B11: Sep 2036 | C11: =F10 | D11: =12*Inputs!$B$4 | E11: =ROUND((C11+D11)*Inputs!$B$9/100,2) | F11: =C11+D11+E11 | G11: =TRIM(IF(AND(C11<15000,F11>=15000),"RM15,000 gate ","")&IF(AND(C11<Inputs!$B$10,F11>=Inputs!$B$10),"Own payment",""))
